weather_for_prebas/__init__.py
weather_for_prebas/clipick_extent_wkt.txt
weather_for_prebas/site_processor.py
weather_for_prebas/sites.py
weather_for_prebas/weather_for_prebas.py
weather_for_prebas-0.1.0.dist-info/WHEEL
weather_for_prebas-0.1.0.dist-info/METADATA
weather_for_prebas-0.1.0.dist-info/RECORD
