Metadata-Version: 2.1
Name: weather-for-prebas
Version: 0.1.0
Summary: 
Author: Jan Pisl
Author-email: jan.pisl@simosol.fi
Requires-Python: >=3.6,<4.0
Classifier: Programming Language :: Python :: 3
Classifier: Programming Language :: Python :: 3.6
Classifier: Programming Language :: Python :: 3.7
Classifier: Programming Language :: Python :: 3.8
Classifier: Programming Language :: Python :: 3.9
Requires-Dist: geopandas (>=0.9.0,<0.10.0)
Requires-Dist: requests (>=2.25.1,<3.0.0)
Requires-Dist: utm (>=0.7.0,<0.8.0)
